whywhytools/__init__.py
whywhytools/json_utils.py
whywhytools/jsonl_utils.py
whywhytools/pickle_utils.py
whywhytools/type_checker.py
whywhytools-0.6.2.dist-info/licenses/LICENSE
whywhytools-0.6.2.dist-info/METADATA
whywhytools-0.6.2.dist-info/WHEEL
whywhytools-0.6.2.dist-info/top_level.txt
whywhytools-0.6.2.dist-info/RECORD
