Metadata-Version: 2.4
Name: whywhytools
Version: 0.6.2
Summary: A lightweight Python package for easy reading and writing of JSON, JSONL, and Pickle files.
Author-email: whywhybug <whywhybug@gmail.com>
License: MIT
Project-URL: Homepage, https://github.com/whywhybug/whywhytools
Requires-Python: >=3.7
License-File: LICENSE
Dynamic: license-file
